README.rst
setup.py
mapletree/__init__.py
mapletree/compat.py
mapletree/driver.py
mapletree/mapletree.py
mapletree/response.py
mapletree.egg-info/PKG-INFO
mapletree.egg-info/SOURCES.txt
mapletree.egg-info/dependency_links.txt
mapletree.egg-info/top_level.txt
mapletree/defaults/__init__.py
mapletree/defaults/request/__init__.py
mapletree/defaults/request/argcontainer.py
mapletree/defaults/request/request.py
mapletree/defaults/request/validators.py
mapletree/defaults/routings/__init__.py
mapletree/defaults/routings/exceptionrouting.py
mapletree/defaults/routings/requestrouting.py
mapletree/defaults/routings/routetree.py
mapletree/helpers/__init__.py
mapletree/helpers/signing.py
mapletree/helpers/stagelocal.py
mapletree/helpers/temptoken.py
mapletree/helpers/threadlocal.py